restless_dj_utils/__init__.py
restless_dj_utils/exceptions.py
restless_dj_utils/__pycache__/__init__.cpython-38.pyc
restless_dj_utils/__pycache__/auth_service.cpython-38.pyc
restless_dj_utils/__pycache__/exceptions.cpython-38.pyc
restless_dj_utils/resources/__init__.py
restless_dj_utils/resources/auth.py
restless_dj_utils/resources/model.py
restless_dj_utils/resources/newrelic.py
restless_dj_utils/resources/paginate.py
restless_dj_utils/resources/__pycache__/__init__.cpython-38.pyc
restless_dj_utils/resources/__pycache__/auth.cpython-38.pyc
restless_dj_utils/resources/__pycache__/model.cpython-38.pyc
restless_dj_utils/resources/__pycache__/newrelic.cpython-38.pyc
restless_dj_utils/resources/__pycache__/paginate.cpython-38.pyc
restless_dj_utils/rest_sessions/__init__.py
restless_dj_utils/rest_sessions/admin.py
restless_dj_utils/rest_sessions/appconfig.py
restless_dj_utils/rest_sessions/backends.py
restless_dj_utils/rest_sessions/conf.py
restless_dj_utils/rest_sessions/manager.py
restless_dj_utils/rest_sessions/tasks.py
restless_dj_utils/rest_sessions/__pycache__/__init__.cpython-38.pyc
restless_dj_utils/rest_sessions/__pycache__/admin.cpython-38.pyc
restless_dj_utils/rest_sessions/__pycache__/backends.cpython-38.pyc
restless_dj_utils/rest_sessions/__pycache__/conf.cpython-38.pyc
restless_dj_utils/rest_sessions/__pycache__/manager.cpython-38.pyc
restless_dj_utils/rest_sessions/__pycache__/service.cpython-38.pyc
restless_dj_utils/rest_sessions/__pycache__/tasks.cpython-38.pyc
restless_dj_utils/rest_sessions/migrations/0001_initial.py
restless_dj_utils/rest_sessions/migrations/0002_auto_20200423_0913.py
restless_dj_utils/rest_sessions/migrations/0003_apisessionusage.py
restless_dj_utils/rest_sessions/migrations/0004_apisession_token_data.py
restless_dj_utils/rest_sessions/migrations/0005_apisession_description.py
restless_dj_utils/rest_sessions/migrations/0006_auto_20201001_1249.py
restless_dj_utils/rest_sessions/migrations/0007_auto_20220311_1134.py
restless_dj_utils-0.2b5.dist-info/LICENSE
restless_dj_utils-0.2b5.dist-info/METADATA
restless_dj_utils-0.2b5.dist-info/WHEEL
restless_dj_utils-0.2b5.dist-info/top_level.txt
restless_dj_utils-0.2b5.dist-info/RECORD
