Metadata-Version: 2.1
Name: restless-dj-utils
Version: 0.2b5
Summary: Restless utils for django API development.
Home-page: http://github.com/AdvancedThreatAnalytics/restless_dj_utils
Author: CriticalStart
Author-email: simon@criticalstart.com
License: MIT
Platform: UNKNOWN
Classifier: Development Status :: 4 - Beta
Classifier: Environment :: Web Environment
Classifier: Framework :: Django
Classifier: Intended Audience :: Developers
Classifier: License :: OSI Approved :: BSD License
Classifier: Operating System :: OS Independent
Classifier: Programming Language :: Python
Classifier: Programming Language :: Python :: 3
Classifier: Topic :: Internet :: WWW/HTTP
License-File: LICENSE
Requires-Dist: django (>=3.2)
Requires-Dist: restless
Requires-Dist: pyjwt (>=2)
Requires-Dist: ua-parser
